tests/func/__init__.py
tests/func/test_path.py
utilp/__init__.py
utilp/_version.py
utilp/classes.py
utilp/decorators.py
utilp/func/__init__.py
utilp/func/path.py
utilp/func/str.py
utilp-0.0.10.dist-info/LICENSE
utilp-0.0.10.dist-info/METADATA
utilp-0.0.10.dist-info/WHEEL
utilp-0.0.10.dist-info/top_level.txt
utilp-0.0.10.dist-info/RECORD
